{
  "id": "lesson12",
  "title": "Aula 12: SI como Vantagem Competitiva",
  "objective": "",
  "content": [
    {
      "type": "html",
      "html": "<!DOCTYPE html>\n<html lang=\"pt-BR\">\n  <head>\n    <meta charset=\"UTF-8\" />\n    <meta name=\"viewport\" content=\"width=device-width, initial-scale=1.0\" />\n    <title>TGS - Aula 12: SI como Vantagem Competitiva</title>\n    <meta\n      name=\"description\"\n      content=\"Aula 12 da disciplina Teoria Geral de Sistemas: como os Sistemas de Informação são usados estrategicamente para gerar vantagem competitiva nas organizações (Porter, Cadeia de Valor, RBV/VRIO, efeitos de rede, governança).\"\n    />\n\n    <!-- Tailwind CSS + plugins (typography + aspect-ratio) -->\n    <!-- NOTE (EN): Unify Tailwind plugins to avoid conflicts -->\n    <script src=\"https://cdn.tailwindcss.com/3.4.1?plugins=typography\"></script>\n\n    <!-- Inter font -->\n    <link rel=\"preconnect\" href=\"https://fonts.googleapis.com\" />\n    <link rel=\"preconnect\" href=\"https://fonts.gstatic.com\" crossorigin />\n    <link\n      href=\"https://fonts.googleapis.com/css2?family=Inter:wght@400;500;600;700&display=swap\"\n      rel=\"stylesheet\"\n    />\n\n    <!-- Font Awesome (icons) -->\n    <link\n      rel=\"stylesheet\"\n      href=\"https://cdnjs.cloudflare.com/ajax/libs/font-awesome/6.4.0/css/all.min.css\"\n    />\n    <link rel=\"stylesheet\" href=\"../css/style.css\" />\n    <link rel=\"stylesheet\" href=\"../css/aula.css\" />\n\n    </head>\n  <body class=\"text-slate-800\">\n    <!-- Header -->\n    <header class=\"bg-white shadow-md\">\n      <div class=\"container mx-auto px-6 py-8\">\n        <h1 class=\"text-4xl font-bold text-sky-800\">\n          Teoria Geral de Sistemas (TGS)\n        </h1>\n        <p class=\"text-xl text-slate-600 mt-2\">\n          Aula 12: Sistemas de Informação como Fonte de Vantagem Competitiva\n        </p>\n      <nav class=\\\"mt-2\\\"><a href=\\\"../index.html\\\" class=\\\"inline-flex items-center gap-2 text-slate-500 hover:text-sky-700 text-sm\\\"><i class=\\\"fa-solid fa-arrow-left\\\"></i><span>Voltar ao Início</span></a></nav>\n    </div>\n    </header>\n\n    <!-- Main -->\n    <main class=\"container mx-auto px-6 py-10\">\n      <div class=\\\"prose prose-slate max-w-none lg:prose-lg aula-prose\\\">\n      <!-- Plano da Aula -->\n      <section\n        id=\"plano-aula\"\n        aria-label=\"Plano da Aula\"\n        class=\"mb-12 bg-sky-50 border border-sky-200 p-8 rounded-2xl shadow-lg\"\n      >\n        <h2 class=\"text-3xl font-bold text-sky-700 mb-6 text-center\">\n          Plano da Aula\n        </h2>\n        <div class=\"grid grid-cols-1 md:grid-cols-2 lg:grid-cols-2 gap-6\">\n          <div\n            class=\"bg-white aula-card p-6 rounded-lg shadow-sm col-span-1 md:col-span-2 lg:col-span-2\"\n          >\n            <h3 class=\"font-semibold text-lg text-sky-800 mb-2\">\n              <i class=\"fa-solid fa-book-open mr-2\" aria-hidden=\"true\"></i\n              >CONTEÚDO\n            </h3>\n            <p class=\"font-bold text-slate-700\">\n              Unidade III – Sistemas de Informação Administrativos\n            </p>\n            <p class=\"text-slate-600 mt-1\">\n              Sistemas de informação como fonte de vantagem competitiva.\n            </p>\n          </div>\n\n          <!-- Objetivos mensuráveis (Bloom) -->\n          <div class=\"bg-white aula-card p-6 rounded-lg shadow-sm\">\n            <h3 class=\"font-semibold text-lg text-sky-800 mb-2\">\n              <i class=\"fa-solid fa-bullseye mr-2\" aria-hidden=\"true\"></i\n              >OBJETIVOS DE APRENDIZAGEM\n            </h3>\n            <ul class=\"list-disc list-inside text-slate-700 space-y-1\">\n              <li>\n                Identificar como SI suportam estratégias genéricas de Porter\n                (custo, diferenciação, foco).\n              </li>\n              <li>\n                Analisar alavancas de SI na\n                <strong>cadeia de valor</strong> (Porter).\n              </li>\n              <li>\n                Avaliar iniciativas de SI com <strong>VRIO</strong> (RBV) para\n                julgar sustentabilidade da vantagem.\n              </li>\n              <li>\n                Propor um experimento com <strong>KPI</strong> e hipótese de\n                impacto mensurável.\n              </li>\n            </ul>\n          </div>\n\n          <div class=\"bg-white aula-card p-6 rounded-lg shadow-sm\">\n            <h3 class=\"font-semibold text-lg text-sky-800 mb-2\">\n              <i class=\"fa-solid fa-gears mr-2\" aria-hidden=\"true\"></i\n              >METODOLOGIA E RECURSOS\n            </h3>\n            <p class=\"text-slate-600\">\n              Aula expositiva com exemplos práticos (Netflix, Nubank, Amazon,\n              Shein), <strong>Jigsaw</strong> em grupo,\n              <strong>VRIO Express</strong> e definição de <strong>KPI</strong>.\n              Recursos: slides, quadro, vídeos curtos sobre uso estratégico de\n              dados.\n            </p>\n          </div>\n        </div>\n      </section>\n\n      <!-- Pergunta Norteadora -->\n      <section\n        id=\"pergunta-norteadora\"\n        class=\"mb-12 callout callout-info\"\n        aria-label=\"Pergunta Norteadora\"\n      >\n        <h3 class=\"font-bold text-lg mb-2\">\n          <i class=\"fa-solid fa-question-circle mr-2\" aria-hidden=\"true\"></i\n          >Pergunta Norteadora\n        </h3>\n        <p>\n          Como uma empresa nativa digital (por ex., Shein), sem lojas físicas,\n          escalou globalmente desafiando incumbentes? Qual o papel dos\n          <strong>dados</strong> e dos\n          <strong>Sistemas de Informação</strong> nessa trajetória?\n        </p>\n      </section>\n\n      <!-- Contexto + Arcabouço -->\n      <section\n        id=\"contexto\"\n        aria-label=\"Contexto Inicial\"\n        class=\"mb-12 bg-white p-8 rounded-lg shadow prose prose-slate max-w-none lg:prose-lg\"\n      >\n        <h2 class=\"text-3xl font-semibold text-slate-800 mb-4\">\n          🏆 SI: de Suporte Operacional a Vantagem Estratégica\n        </h2>\n        <p>\n          Vantagem competitiva (Porter) é superar concorrentes de forma\n          sustentável — por custo, diferenciação ou foco. Na perspectiva\n          <strong>RBV</strong> (Resource-Based View), a sustentabilidade depende\n          de recursos/capacidades que sejam <strong>Valiosos</strong>,\n          <strong>Raros</strong>, <strong>Difíceis de Imitar</strong> e com\n          <strong>Organização</strong> para capturar valor\n          (<strong>VRIO</strong>).\n        </p>\n        <p>\n          SI isoladamente tende a comoditizar. O que sustenta a vantagem é a\n          <strong>capacidade</strong> de aprender rápido (dados &amp;\n          experimentação), operar com excelência (processos), orquestrar\n          ecossistemas (efeitos de rede) e manter\n          <strong>governança/ética/LGPD</strong> para preservar a confiança.\n        </p>\n      </section>\n\n      <!-- Mapa Conceitual (SVG acessível) -->\n      <section id=\"mapa-conceitual\" class=\"mb-12\">\n        <h2\n          class=\"text-3xl font-semibold text-slate-800 border-b-2 border-sky-500 pb-2 mb-6\"\n        >\n          Mapa Conceitual: Estratégia ↔ SI ↔ Valor\n        </h2>\n        <div class=\"bg-white aula-card p-6 rounded-lg shadow text-center\">\n          <!-- NOTE (EN): Simple, high-contrast conceptual map -->\n          <svg\n            viewBox=\"0 0 900 340\"\n            role=\"img\"\n            aria-labelledby=\"mcTitle mcDesc\"\n            class=\"w-full h-auto\"\n          >\n            <title id=\"mcTitle\">\n              Mapa Conceitual de Vantagem Competitiva com SI\n            </title>\n            <desc id=\"mcDesc\">\n              Nós conectando Estratégias Genéricas, Cadeia de Valor, SI/Dados,\n              VRIO, KPIs e Governança/Ética (LGPD).\n            </desc>\n            <!-- Nodes -->\n            <defs>\n              <filter id=\"shadow\" x=\"-10%\" y=\"-10%\" width=\"130%\" height=\"130%\">\n                <feDropShadow\n                  dx=\"0\"\n                  dy=\"1\"\n                  stdDeviation=\"2\"\n                  flood-color=\"#94a3b8\"\n                  flood-opacity=\"0.6\"\n                />\n              </filter>\n            </defs>\n\n            <!-- Boxes -->\n            <g filter=\"url(#shadow)\">\n              <rect\n                x=\"30\"\n                y=\"30\"\n                width=\"230\"\n                height=\"70\"\n                rx=\"12\"\n                fill=\"#ecfeff\"\n                stroke=\"#06b6d4\"\n              />\n              <text\n                x=\"145\"\n                y=\"65\"\n                text-anchor=\"middle\"\n                font-size=\"16\"\n                fill=\"#0e7490\"\n              >\n                Estratégias (Porter)\n              </text>\n              <text\n                x=\"145\"\n                y=\"85\"\n                text-anchor=\"middle\"\n                font-size=\"12\"\n                fill=\"#0e7490\"\n              >\n                Custo • Diferenciação • Foco\n              </text>\n\n              <rect\n                x=\"340\"\n                y=\"30\"\n                width=\"220\"\n                height=\"70\"\n                rx=\"12\"\n                fill=\"#f0f9ff\"\n                stroke=\"#7dd3fc\"\n              />\n              <text\n                x=\"450\"\n                y=\"65\"\n                text-anchor=\"middle\"\n                font-size=\"16\"\n                fill=\"#0369a1\"\n              >\n                Cadeia de Valor\n              </text>\n              <text\n                x=\"450\"\n                y=\"85\"\n                text-anchor=\"middle\"\n                font-size=\"12\"\n                fill=\"#0369a1\"\n              >\n                Onde SI reduz custo/aumenta valor\n              </text>\n\n              <rect\n                x=\"650\"\n                y=\"30\"\n                width=\"220\"\n                height=\"70\"\n                rx=\"12\"\n                fill=\"#f0fdf4\"\n                stroke=\"#6ee7b7\"\n              />\n              <text\n                x=\"760\"\n                y=\"65\"\n                text-anchor=\"middle\"\n                font-size=\"16\"\n                fill=\"#065f46\"\n              >\n                SI &amp; Dados\n              </text>\n              <text\n                x=\"760\"\n                y=\"85\"\n                text-anchor=\"middle\"\n                font-size=\"12\"\n                fill=\"#065f46\"\n              >\n                Analytics • Automação • Plataforma\n              </text>\n\n              <rect\n                x=\"120\"\n                y=\"180\"\n                width=\"230\"\n                height=\"70\"\n                rx=\"12\"\n                fill=\"#fef9c3\"\n                stroke=\"#f59e0b\"\n              />\n              <text\n                x=\"235\"\n                y=\"215\"\n                text-anchor=\"middle\"\n                font-size=\"16\"\n                fill=\"#92400e\"\n              >\n                VRIO (RBV)\n              </text>\n              <text\n                x=\"235\"\n                y=\"235\"\n                text-anchor=\"middle\"\n                font-size=\"12\"\n                fill=\"#92400e\"\n              >\n                Valioso • Raro • Inimitável • Organizado\n              </text>\n\n              <rect\n                x=\"360\"\n                y=\"180\"\n                width=\"180\"\n                height=\"70\"\n                rx=\"12\"\n                fill=\"#e0f2fe\"\n                stroke=\"#38bdf8\"\n              />\n              <text\n                x=\"450\"\n                y=\"215\"\n                text-anchor=\"middle\"\n                font-size=\"16\"\n                fill=\"#0c4a6e\"\n              >\n                KPIs\n              </text>\n              <text\n                x=\"450\"\n                y=\"235\"\n                text-anchor=\"middle\"\n                font-size=\"12\"\n                fill=\"#0c4a6e\"\n              >\n                Conversão • Churn • Margem • OTIF\n              </text>\n\n              <rect\n                x=\"570\"\n                y=\"180\"\n                width=\"260\"\n                height=\"70\"\n                rx=\"12\"\n                fill=\"#fee2e2\"\n                stroke=\"#fca5a5\"\n              />\n              <text\n                x=\"700\"\n                y=\"215\"\n                text-anchor=\"middle\"\n                font-size=\"16\"\n                fill=\"#7f1d1d\"\n              >\n                Governança &amp; LGPD\n              </text>\n              <text\n                x=\"700\"\n                y=\"235\"\n                text-anchor=\"middle\"\n                font-size=\"12\"\n                fill=\"#7f1d1d\"\n              >\n                Ética • Confiança • Sustentabilidade\n              </text>\n            </g>\n\n            <!-- Arrows -->\n            <defs>\n              <marker\n                id=\"arrow\"\n                markerWidth=\"8\"\n                markerHeight=\"8\"\n                refX=\"6\"\n                refY=\"4\"\n                orient=\"auto-start-reverse\"\n              >\n                <path d=\"M0,0 L0,8 L8,4 z\" fill=\"#64748b\"></path>\n              </marker>\n            </defs>\n            <line\n              x1=\"260\"\n              y1=\"65\"\n              x2=\"340\"\n              y2=\"65\"\n              stroke=\"#64748b\"\n              stroke-width=\"2\"\n              marker-end=\"url(#arrow)\"\n            />\n            <line\n              x1=\"560\"\n              y1=\"65\"\n              x2=\"650\"\n              y2=\"65\"\n              stroke=\"#64748b\"\n              stroke-width=\"2\"\n              marker-end=\"url(#arrow)\"\n            />\n            <line\n              x1=\"760\"\n              y1=\"100\"\n              x2=\"700\"\n              y2=\"180\"\n              stroke=\"#64748b\"\n              stroke-width=\"2\"\n              marker-end=\"url(#arrow)\"\n            />\n            <line\n              x1=\"450\"\n              y1=\"100\"\n              x2=\"450\"\n              y2=\"180\"\n              stroke=\"#64748b\"\n              stroke-width=\"2\"\n              marker-end=\"url(#arrow)\"\n            />\n            <line\n              x1=\"340\"\n              y1=\"100\"\n              x2=\"235\"\n              y2=\"180\"\n              stroke=\"#64748b\"\n              stroke-width=\"2\"\n              marker-end=\"url(#arrow)\"\n            />\n          </svg>\n        </div>\n      </section>\n\n      <!-- SECTION: Guia detalhado do Mapa Conceitual (Estratégia ↔ SI ↔ Valor) -->\n      <section\n        id=\"guia-conceitos\"\n        aria-label=\"Guia dos Conceitos do Mapa Estratégia ↔ SI ↔ Valor\"\n        class=\"mb-12 bg-white p-8 rounded-2xl shadow prose prose-slate max-w-none lg:prose-lg\"\n      >\n        <!-- NOTE (EN): This section explains each concept from the conceptual map with examples and references. -->\n        <h2\n          class=\"text-3xl font-semibold text-slate-800 border-b-2 border-sky-500 pb-2 mb-6\"\n        >\n          Guia do Mapa: Estratégia ↔ SI ↔ Valor\n        </h2>\n\n        <!-- Estratégia -->\n        <h3 class=\"text-2xl font-bold text-slate-800\">1) Estratégia</h3>\n        <p>\n          Em termos clássicos, empresas buscam vantagem competitiva por três\n          vias:\n          <strong>liderança em custo</strong>, <strong>diferenciação</strong> e\n          <strong>foco (nicho)</strong>. Na prática: reduzir custos ponta a\n          ponta (custo), criar experiências e atributos únicos (diferenciação)\n          ou dominar um segmento específico (foco).\n        </p>\n        <p>\n          A <strong>Cadeia de Valor</strong> ajuda a enxergar onde a vantagem\n          nasce: um sistema de atividades interligadas (logística, operações,\n          marketing, TI, etc.) que, combinadas, criam valor superior ao custo.\n          Mapear essas atividades mostra onde investir em dados, automação e\n          análises para aumentar margens ou elevar a percepção de valor do\n          cliente.\n        </p>\n        <div class=\"bg-sky-50 border border-sky-200 rounded-xl p-4 not-prose\">\n          <!-- NOTE (EN): Short, concrete examples. -->\n          <p class=\"font-semibold text-slate-700\">Exemplos rápidos</p>\n          <ul class=\"list-disc list-inside text-slate-700\">\n            <li>\n              <strong>Custo:</strong> otimização de rotas e estoque reduzindo\n              km, tempo e rupturas.\n            </li>\n            <li>\n              <strong>Diferenciação:</strong> recomendações personalizadas\n              aumentam relevância e retenção.\n            </li>\n            <li>\n              <strong>Foco:</strong> produto/serviço digital desenhado para um\n              público específico com dores claras.\n            </li>\n          </ul>\n        </div>\n\n        <!-- SI & Dados -->\n        <h3 class=\"text-2xl font-bold text-slate-800 mt-10\">\n          2) SI & Dados (como a TI habilita a estratégia)\n        </h3>\n        <p>\n          Sistemas de Informação (SI) conectam e potencializam a estratégia ao\n          <strong>integrar processos</strong>,\n          <strong>gerar informação de qualidade</strong> e\n          <strong>orquestrar decisões</strong>. Clássicos da estratégia mostram\n          como TI reconfigura cadeias de valor e a competição ao alterar custos\n          de transação, informação e coordenação.\n        </p>\n\n        <h4 class=\"text-xl font-semibold text-slate-800 mt-6\">\n          2.1 Analytics/BI\n        </h4>\n        <p>\n          Consolida dados (OLTP → DWH/OLAP) para responder <em>o quê</em> e\n          <em>por quê</em> está acontecendo, suportando decisões\n          <em>semiestruturadas</em> (nível tático). Indicadores e relatórios\n          alinham a execução à estratégia.\n        </p>\n\n        <h4 class=\"text-xl font-semibold text-slate-800 mt-4\">\n          2.2 Automação & Processos\n        </h4>\n        <p>\n          Workflow, RPA e integrações reduzem tempos de ciclo, erros e custos\n          operacionais — alavancas diretas para\n          <strong>liderança em custo</strong>. Ao mesmo tempo, padronização\n          eleva a qualidade percebida (apoio à <strong>diferenciação</strong>).\n        </p>\n\n        <h4 class=\"text-xl font-semibold text-slate-800 mt-4\">\n          2.3 Plataformas & Efeitos de Rede\n        </h4>\n        <p>\n          Em plataformas digitais, o <strong>valor</strong> para cada usuário\n          cresce à medida que aumenta o número de usuários/participantes (<em\n            >efeitos de rede</em\n          >). Essa dinâmica pode criar vantagens difíceis de imitar (ex.:\n          marketplaces, apps de mensagens, ridesharing).\n        </p>\n\n        <h4 class=\"text-xl font-semibold text-slate-800 mt-4\">\n          2.4 Governança de Dados & LGPD\n        </h4>\n        <p>\n          <strong>Governança de dados</strong> define políticas, papéis e\n          controles para garantir dados\n          <em>confiáveis, seguros e utilizáveis</em> em toda a organização (base\n          do valor analítico). Frameworks como o DAMA-DMBOK sistematizam essas\n          práticas.\n        </p>\n        <p>\n          No Brasil, a <strong>LGPD (Lei nº 13.709/2018)</strong> regula o\n          tratamento de dados pessoais e protege direitos fundamentais. Projetos\n          de SI que geram vantagem devem, portanto, nascer com\n          <em>privacidade e conformidade</em> desde o design.\n        </p>\n\n        <!-- Valor -->\n        <h3 class=\"text-2xl font-bold text-slate-800 mt-10\">\n          3) Valor (como medir e demonstrar resultados)\n        </h3>\n        <p>\n          <strong>KPIs</strong> são indicadores-chave que acompanham objetivos\n          estratégicos e permitem avaliar impacto (financeiro, clientes,\n          processos, aprendizado/inovação). Bons SI trazem KPIs confiáveis,\n          tempestivos e acionáveis.\n        </p>\n        <div class=\"grid grid-cols-1 md:grid-cols-2 gap-6 not-prose\">\n          <!-- NOTE (EN): KPI examples by strategic aim. -->\n          <div class=\"border border-slate-200 rounded-xl p-4\">\n            <p class=\"font-semibold text-slate-700\">\n              Exemplos de KPIs por objetivo\n            </p>\n            <ul class=\"list-disc list-inside text-slate-700\">\n              <li>\n                <strong>Custo:</strong> Custo por pedido, % OTIF, tempo de\n                ciclo.\n              </li>\n              <li>\n                <strong>Diferenciação:</strong> NPS/CSAT, churn, LTV,\n                engajamento.\n              </li>\n              <li>\n                <strong>Foco:</strong> participação no nicho, margem média por\n                segmento, CAC no nicho.\n              </li>\n            </ul>\n          </div>\n          <div class=\"border border-slate-200 rounded-xl p-4\">\n            <p class=\"font-semibold text-slate-700\">Boas práticas (KPIs)</p>\n            <ul class=\"list-disc list-inside text-slate-700\">\n              <li>Definir <em>owner</em>, fórmula, fonte e frequência.</li>\n              <li>\n                Preferir indicadores <em>leading</em> para ação, não só\n                <em>lagging</em>.\n              </li>\n              <li>Ligar o KPI a iniciativas e metas claras (OKRs/BSC).</li>\n            </ul>\n          </div>\n        </div>\n\n        <!-- Recursos e Vantagem Sustentável (VRIO) -->\n        <h3 class=\"text-2xl font-bold text-slate-800 mt-10\">\n          4) Recursos que sustentam a vantagem (VRIO)\n        </h3>\n        <p>\n          Para que a vantagem seja <em>sustentável</em>, os recursos/capacidades\n          de SI precisam ser\n          <strong>Valiosos, Raros, Difíceis de Imitar</strong> e a organização\n          deve estar preparada para <strong>Explorá-los</strong> (VRIO).\n          Exemplos: dados proprietários de alta qualidade, modelos analíticos\n          exclusivos, engenharia de plataforma e cultura orientada a\n          experimentos.\n        </p>\n\n        <!-- Fechando o ciclo -->\n        <h3 class=\"text-2xl font-bold text-slate-800 mt-10\">\n          5) Conectando tudo (passo a passo)\n        </h3>\n        <ol>\n          <li>\n            <strong>Escolha estratégica:</strong> Onde competir (segmento) e\n            como vencer (custo, diferenciação, foco).\n          </li>\n          <li>\n            <strong>Desenho do SI:</strong> Quais dados, integrações e\n            automações suportam a cadeia de valor?\n          </li>\n          <li>\n            <strong>Medição de valor:</strong> KPIs alinhados à estratégia, com\n            governança e conformidade.\n          </li>\n          <li>\n            <strong>Sustentação:</strong> Desenvolver recursos VRIO (dados,\n            modelos, talentos, cultura).\n          </li>\n          <li>\n            <strong>Escala:</strong> Se houver plataforma, explorar efeitos de\n            rede para vantagem cumulativa.\n          </li>\n        </ol>\n\n        <!-- Nota final -->\n        <div class=\"callout callout-info mt-6 not-prose\">\n          <!-- NOTE (EN): Short reminder about ethics and compliance. -->\n          <p class=\"font-semibold\">\n            Lembrete: vantagem competitiva baseada em dados precisa ser também\n            <em>ética</em> e <em>legal</em> — qualidade, privacidade e\n            transparência não são opcionais (LGPD).\n          </p>\n        </div>\n      </section>\n\n      <!-- Estratégias Competitivas (alavancas + risco/mitigação) -->\n      <section\n        id=\"estrategias-competitivas\"\n        aria-label=\"Estratégias Competitivas e o Papel do SI\"\n        class=\"mb-12\"\n      >\n        <h2\n          class=\"text-3xl font-semibold text-slate-800 border-b-2 border-sky-500 pb-2 mb-8\"\n        >\n          Como os SI Habilitam Estratégias Competitivas\n        </h2>\n        <p class=\"text-lg text-slate-600 mb-6\">\n          Os SI viabilizam <em>custo</em>, <em>diferenciação</em> e\n          <em>foco</em> por meio de alavancas operacionais e informacionais.\n        </p>\n        <ul class=\"grid grid-cols-1 md:grid-cols-3 gap-6\">\n          <li class=\"bg-white aula-card p-5 rounded-lg border border-slate-200\">\n            <h3 class=\"text-xl font-bold text-slate-700\">Liderança em Custo</h3>\n            <p>\n              <em>Alavancas:</em> automação, predição, roteirização, estoque\n              enxuto.\n            </p>\n            <p class=\"text-sm mt-2\">\n              <em>Risco:</em> comoditização. <em>Mitigação:</em> excelência\n              operacional + dados proprietários.\n            </p>\n            <p class=\"text-sm mt-1\">\n              <strong>Ex.:</strong> logística preditiva e WMS/OMS integrados\n              reduzem desperdícios.\n            </p>\n          </li>\n          <li class=\"bg-white aula-card p-5 rounded-lg border border-slate-200\">\n            <h3 class=\"text-xl font-bold text-slate-700\">Diferenciação</h3>\n            <p>\n              <em>Alavancas:</em> personalização, UX superior,\n              conteúdos/serviços exclusivos.\n            </p>\n            <p class=\"text-sm mt-2\">\n              <em>Risco:</em> cópia rápida. <em>Mitigação:</em> marca +\n              comunidade + dados de uso.\n            </p>\n            <p class=\"text-sm mt-1\">\n              <strong>Ex.:</strong> recomendação e testes A/B aceleram\n              aprendizado de produto.\n            </p>\n          </li>\n          <li class=\"bg-white aula-card p-5 rounded-lg border border-slate-200\">\n            <h3 class=\"text-xl font-bold text-slate-700\">Foco (Nicho)</h3>\n            <p>\n              <em>Alavancas:</em> jornada específica, dados de domínio, serviço\n              sob medida.\n            </p>\n            <p class=\"text-sm mt-2\">\n              <em>Risco:</em> saturação do nicho. <em>Mitigação:</em> expansão\n              adjacente orientada a dados.\n            </p>\n            <p class=\"text-sm mt-1\">\n              <strong>Ex.:</strong> fintech digital focada em segmento\n              subatendido com UX simples.\n            </p>\n          </li>\n        </ul>\n      </section>\n\n      <!-- Laboratório de Métricas (KPI x Alavanca de SI) -->\n      <section id=\"lab-metricas\" class=\"mb-12 bg-white p-8 rounded-lg shadow\">\n        <h2 class=\"text-2xl font-semibold text-slate-800 mb-4\">\n          🔬 Laboratório de Métricas: de SI a Impacto\n        </h2>\n        <p class=\"text-slate-600 mb-4\">\n          Relacione alavancas de SI com <strong>KPIs</strong> de negócio. Isso\n          ajuda a justificar “por que” a iniciativa gera vantagem.\n        </p>\n        <div class=\"overflow-x-auto\">\n          <table class=\"min-w-full text-sm border border-slate-200 rounded-lg\">\n            <thead class=\"bg-slate-100 text-slate-700\">\n              <tr>\n                <th class=\"px-4 py-2 text-left\">KPI</th>\n                <th class=\"px-4 py-2 text-left\">Alavanca de SI</th>\n                <th class=\"px-4 py-2 text-left\">Hipótese de Impacto</th>\n              </tr>\n            </thead>\n            <tbody class=\"divide-y divide-slate-200\">\n              <tr>\n                <td class=\"px-4 py-2\">Conversão</td>\n                <td class=\"px-4 py-2\">Recomendação/Personalização</td>\n                <td class=\"px-4 py-2\">\n                  “Se personalizarmos a vitrine, a conversão ↑ 10% em 8\n                  semanas.”\n                </td>\n              </tr>\n              <tr>\n                <td class=\"px-4 py-2\">Churn</td>\n                <td class=\"px-4 py-2\">Propensão + Retenção proativa</td>\n                <td class=\"px-4 py-2\">\n                  “Se atuarmos em risco alto, churn ↓ 15% em 1 trimestre.”\n                </td>\n              </tr>\n              <tr>\n                <td class=\"px-4 py-2\">Margem</td>\n                <td class=\"px-4 py-2\">Precificação dinâmica</td>\n                <td class=\"px-4 py-2\">\n                  “Se otimizarmos preço por elasticidade, margem ↑ 2 p.p.”\n                </td>\n              </tr>\n              <tr>\n                <td class=\"px-4 py-2\">OTIF</td>\n                <td class=\"px-4 py-2\">Previsão de demanda + roteirização</td>\n                <td class=\"px-4 py-2\">\n                  “Se roteirizarmos com restrições, OTIF ↑ 8%.”\n                </td>\n              </tr>\n            </tbody>\n          </table>\n        </div>\n      </section>\n\n      <!-- VRIO (flash) -->\n      <section id=\"vrio\" class=\"mb-12 bg-white p-8 rounded-lg shadow\">\n        <h2 class=\"text-2xl font-semibold text-slate-800 mb-4\">\n          🧭 VRIO: Sustentando a Vantagem\n        </h2>\n        <div class=\"overflow-x-auto\">\n          <table class=\"min-w-full text-sm border border-slate-200 rounded-lg\">\n            <thead class=\"bg-slate-100\">\n              <tr>\n                <th class=\"px-3 py-2 text-left\">Recurso/Capacidade</th>\n                <th class=\"px-3 py-2\">V</th>\n                <th class=\"px-3 py-2\">R</th>\n                <th class=\"px-3 py-2\">I</th>\n                <th class=\"px-3 py-2\">O</th>\n                <th class=\"px-3 py-2 text-left\">Implicação</th>\n              </tr>\n            </thead>\n            <tbody class=\"divide-y\">\n              <tr>\n                <td class=\"px-3 py-2\">Dados proprietários de comportamento</td>\n                <td class=\"text-center\">✓</td>\n                <td class=\"text-center\">✓</td>\n                <td class=\"text-center\">△</td>\n                <td class=\"text-center\">✓</td>\n                <td class=\"px-3 py-2\">\n                  Vantagem potencial (depende de capacidade de uso)\n                </td>\n              </tr>\n              <tr>\n                <td class=\"px-3 py-2\">Plataforma com efeitos de rede</td>\n                <td class=\"text-center\">✓</td>\n                <td class=\"text-center\">✓</td>\n                <td class=\"text-center\">✓</td>\n                <td class=\"text-center\">✓</td>\n                <td class=\"px-3 py-2\">\n                  Vantagem sustentável (difícil de “clonar”)\n                </td>\n              </tr>\n              <tr>\n                <td class=\"px-3 py-2\">\n                  Infraestrutura em nuvem “comoditizada”\n                </td>\n                <td class=\"text-center\">✓</td>\n                <td class=\"text-center\">✗</td>\n                <td class=\"text-center\">✗</td>\n                <td class=\"text-center\">✓</td>\n                <td class=\"px-3 py-2\">Paridade competitiva (não diferencia)</td>\n              </tr>\n            </tbody>\n          </table>\n        </div>\n      </section>\n\n      <!-- Checklist de Sustentabilidade -->\n      <section\n        id=\"checklist\"\n        class=\"mb-12 bg-white p-8 rounded-lg shadow prose prose-slate max-w-none lg:prose-lg\"\n      >\n        <h2 class=\"text-2xl font-semibold text-slate-800 mb-2\">\n          ✅ Checklist de Sustentabilidade da Vantagem\n        </h2>\n        <ul>\n          <li>\n            O ativo informacional é <strong>proprietário</strong> (ou facilmente\n            replicável)?\n          </li>\n          <li>\n            Temos <strong>capacidade</strong> de explorá-lo (talentos,\n            processos, MLOps, produto)?\n          </li>\n          <li>\n            Existe <strong>efeito de rede</strong> ou custos de troca do\n            cliente?\n          </li>\n          <li>\n            Há <strong>governança/ética/LGPD</strong> para sustentar confiança?\n          </li>\n          <li>\n            Aprendemos com <strong>experimentos</strong> (ciclo ágil de dados)?\n          </li>\n        </ul>\n      </section>\n\n      <!-- Metodologia Ativa -->\n      <section\n        id=\"metodologia-ativa\"\n        aria-label=\"Metodologia Ativa\"\n        class=\"mb-12 callout callout-practice\"\n      >\n        <h2 class=\"text-2xl font-bold mb-2\">\n          <i class=\"fa-solid fa-comments mr-2\" aria-hidden=\"true\"></i>Jigsaw +\n          VRIO Express + KPI (30–35 min)\n        </h2>\n        <ol class=\"list-decimal list-inside space-y-2\">\n          <li>\n            <strong>Jigsaw (10’):</strong> grupos (Netflix, Amazon,\n            Nubank/Shein) mapeiam <em>2 alavancas</em> na cadeia de valor.\n          </li>\n          <li>\n            <strong>VRIO Express (10’):</strong> cada grupo classifica\n            <em>1 ativo</em> (dados, algoritmo, parceria) em V/R/I/O.\n          </li>\n          <li>\n            <strong>KPI &amp; hipótese (10–15’):</strong> definem\n            <em>1 KPI</em> e <em>1 hipótese</em> de impacto (quanto/tempo).\n          </li>\n        </ol>\n        <!-- Canvas orientador -->\n        <div class=\"bg-white/50 p-4 rounded-md mt-3\">\n          <h3 class=\"font-semibold text-slate-800\">Canvas VRIO + KPI (guia)</h3>\n          <ul class=\"list-disc list-inside text-slate-700\">\n            <li>\n              <strong>Ativo informacional:</strong> (ex.: motor de recomendação)\n            </li>\n            <li>\n              <strong>VRIO:</strong> V [ ] R [ ] I [ ] O [ ] – justificar em 2\n              linhas.\n            </li>\n            <li>\n              <strong>KPI:</strong> (conversão, churn, margem, OTIF, LTV/CAC…)\n            </li>\n            <li>\n              <strong>Hipótese:</strong> “Se fizermos X, então Y melhora em Z%\n              em T semanas.”\n            </li>\n          </ul>\n        </div>\n      </section>\n\n      <!-- TED -->\n      <section\n        id=\"tarefa\"\n        aria-label=\"Tarefa da Aula\"\n        class=\"mb-12 prose prose-slate max-w-none lg:prose-lg\"\n      >\n        <h2\n          class=\"text-3xl font-semibold text-slate-800 border-b-2 border-sky-500 pb-2 mb-4\"\n        >\n          📝 Tarefa (TED): Atividade Escrita\n        </h2>\n        <div class=\"bg-white aula-card p-8 rounded-lg shadow not-prose\">\n          <p class=\"text-lg leading-relaxed mb-4\">\n            Responda no AVA (mín. 8 linhas):\n          </p>\n          <blockquote class=\"text-lg italic text-slate-700 my-2\">\n            “Uma startup pode superar grandes empresas com o uso estratégico da\n            informação? Dê um exemplo real para justificar.”\n          </blockquote>\n          <div class=\"bg-slate-50 p-4 rounded-md\">\n            <p class=\"font-semibold\">Inclua na resposta:</p>\n            <ol class=\"list-decimal list-inside mt-2 space-y-2\">\n              <li><strong>Caso real</strong> (qual/onde/quando).</li>\n              <li><strong>Alavanca de SI</strong> (o que/como).</li>\n              <li>\n                <strong>VRIO</strong> (qual dimensão sustenta a vantagem?).\n              </li>\n              <li><strong>Métrica</strong> (KPI impactada e por quê).</li>\n            </ol>\n          </div>\n          <!-- Rubrica -->\n          <h3 class=\"font-semibold text-slate-800 mt-5\">📏 Rubrica (0–10)</h3>\n          <div class=\"overflow-x-auto\">\n            <table\n              class=\"min-w-full text-sm border border-slate-200 rounded-lg\"\n            >\n              <thead class=\"bg-slate-100 text-slate-700\">\n                <tr>\n                  <th class=\"px-3 py-2 text-left\">Critério</th>\n                  <th class=\"px-3 py-2\">0</th>\n                  <th class=\"px-3 py-2\">1</th>\n                  <th class=\"px-3 py-2\">2</th>\n                  <th class=\"px-3 py-2\">3</th>\n                </tr>\n              </thead>\n              <tbody class=\"divide-y divide-slate-200\">\n                <tr>\n                  <td class=\"px-3 py-2\">Exemplo real (contexto)</td>\n                  <td class=\"px-3 py-2\">Ausente</td>\n                  <td class=\"px-3 py-2\">Vago</td>\n                  <td class=\"px-3 py-2\">Adequado</td>\n                  <td class=\"px-3 py-2\">Específico/atual</td>\n                </tr>\n                <tr>\n                  <td class=\"px-3 py-2\">Alavanca de SI (clareza)</td>\n                  <td>Ausente</td>\n                  <td>Genérica</td>\n                  <td>Clara</td>\n                  <td>Clara e conectada à estratégia</td>\n                </tr>\n                <tr>\n                  <td class=\"px-3 py-2\">VRIO (análise)</td>\n                  <td>Ausente</td>\n                  <td>Parcial</td>\n                  <td>Correta</td>\n                  <td>Correta e bem justificada</td>\n                </tr>\n                <tr>\n                  <td class=\"px-3 py-2\">Métrica/KPI</td>\n                  <td>Ausente</td>\n                  <td>Genérica</td>\n                  <td>Adequada</td>\n                  <td>Adequada + plausível</td>\n                </tr>\n              </tbody>\n            </table>\n            <p class=\"text-xs text-slate-500 mt-2\">\n              Nota = soma (máx. 12) normalizada para 10.\n            </p>\n          </div>\n          <p class=\"mt-4 font-semibold\">\n            <strong>Entrega:</strong> Poste a sua resposta no fórum da\n            disciplina no AVA.\n          </p>\n        </div>\n      </section>\n\n      <!-- Mini-Quiz -->\n      <section id=\"quiz\" class=\"mb-12\" aria-label=\"Quiz de Autoavaliação\">\n        <h2\n          class=\"text-3xl font-semibold text-slate-800 border-b-2 border-sky-500 pb-2 mb-6\"\n        >\n          🧐 Mini-Quiz de Autoavaliação\n        </h2>\n        <div class=\"space-y-4\">\n          <details>\n            <summary>\n              1) Uma companhia aérea de baixo custo que usa SI para otimizar\n              ocupação e tempo em solo segue qual estratégia?\n            </summary>\n            <div class=\"quiz-answer\">\n              <p><strong>Resposta:</strong> Liderança em Custo.</p>\n            </div>\n          </details>\n          <details>\n            <summary>\n              2) O feed altamente personalizado de uma plataforma social é\n              exemplo de SI a serviço da...\n            </summary>\n            <div class=\"quiz-answer\">\n              <p><strong>Resposta:</strong> Diferenciação.</p>\n            </div>\n          </details>\n          <details>\n            <summary>\n              3) VRIO: Dados proprietários sem processos/competências para\n              explorá-los são...\n            </summary>\n            <div class=\"quiz-answer\">\n              <p>\n                <strong>Resposta:</strong> Valiosos, porém sem “O” (Organização)\n                — vantagem não sustentada.\n              </p>\n            </div>\n          </details>\n          <details>\n            <summary>\n              4) Verdadeiro/Falso: Compliance (LGPD) e transparência podem se\n              tornar diferenciais competitivos.\n            </summary>\n            <div class=\"quiz-answer\">\n              <p>\n                <strong>Resposta:</strong> Verdadeiro. Confiança impacta\n                aquisição/retensão e reduz risco.\n              </p>\n            </div>\n          </details>\n          <details>\n            <summary>5) Em “foco (nicho)”, qual risco e como mitigar?</summary>\n            <div class=\"quiz-answer\">\n              <p>\n                <strong>Resposta:</strong> Saturação do nicho; mitigar com\n                expansão adjacente orientada a dados.\n              </p>\n            </div>\n          </details>\n        </div>\n      </section>\n\n      <!-- Glossário breve -->\n      <section\n        id=\"glossario\"\n        class=\"mb-12 bg-slate-50 border border-slate-200 p-8 rounded-2xl\"\n      >\n        <h2 class=\"text-2xl font-semibold text-slate-800 mb-4\">\n          📑 Glossário Rápido\n        </h2>\n        <ul class=\"list-disc list-inside text-slate-700\">\n          <li>\n            <strong>RBV/VRIO:</strong> visão baseada em recursos; Valioso, Raro,\n            Inimitável, Organizado.\n          </li>\n          <li>\n            <strong>Cadeia de Valor:</strong> atividades onde SI reduzem\n            custo/aumentam valor.\n          </li>\n          <li>\n            <strong>Efeito de Rede:</strong> valor cresce com nº de usuários\n            (plataformas).\n          </li>\n          <li>\n            <strong>LGPD:</strong> lei de proteção de dados — base de\n            confiança/ética.\n          </li>\n        </ul>\n      </section>\n\n      <!-- Bibliografia -->\n      <section\n        id=\"bibliografia\"\n        aria-label=\"Bibliografia\"\n        class=\"prose prose-slate max-w-none lg:prose-lg\"\n      >\n        <h2\n          class=\"text-3xl font-semibold text-slate-800 border-b-2 border-sky-500 pb-2 mb-4\"\n        >\n          📚 Bibliografia\n        </h2>\n        <div class=\"bg-white aula-card p-8 rounded-lg shadow space-y-4 not-prose\">\n          <p>\n            <strong>SILVA, K.C.N.D.; BARBOSA, C.; JUNIOR, R.S.C.</strong>\n            <em>Sistemas de informações gerenciais.</em> Porto Alegre: Grupo A,\n            2019.\n          </p>\n          <p>\n            <strong>STAIR, Ralph M.; REYNOLDS, George W.</strong>\n            <em>Princípios de sistemas de informação.</em> 14. ed. São Paulo:\n            Cengage Learning, 2021.\n          </p>\n          <p class=\"text-sm text-slate-500\">\n            Leitura complementar sugerida: PORTER, M. E.\n            <em>Vantagem Competitiva</em>; BARNEY, J. B.\n            <em>Firm Resources and Sustained Competitive Advantage</em>.\n          </p>\n        </div>\n      </section>\n          </div>\n    </main>\n\n    <!-- Footer -->\n    <footer class=\"bg-slate-800 text-white mt-12\" role=\"contentinfo\">\n      <div class=\"container mx-auto px-6 py-4 text-center\">\n        <p>&copy; 2025 - Disciplina de Teoria Geral de Sistemas</p>\n        <p class=\"text-sm text-slate-400\">\n          Material desenvolvido para o curso de Sistemas de Informação.\n        </p>\n      </div>\n    </footer>\n  </body>\n</html>\n"
    }
  ]
}
